racp/__init__.py
racp/crawl.py
racp/data.py
racp/retriver.py
racp/utils.py
racp-0.1.2.dist-info/LICENSE
racp-0.1.2.dist-info/METADATA
racp-0.1.2.dist-info/WHEEL
racp-0.1.2.dist-info/top_level.txt
racp-0.1.2.dist-info/RECORD
